LICENSE
MANIFEST.in
README.md
config-example.yaml
setup.py
regindexer/__init__.py
regindexer/cli.py
regindexer/config.py
regindexer/daemon.py
regindexer/indexer.py
regindexer/tag_pattern.py
regindexer.egg-info/PKG-INFO
regindexer.egg-info/SOURCES.txt
regindexer.egg-info/dependency_links.txt
regindexer.egg-info/entry_points.txt
regindexer.egg-info/requires.txt
regindexer.egg-info/top_level.txt